uipath_openai_agents/__init__.py
uipath_openai_agents/middlewares.py
uipath_openai_agents/py.typed
uipath_openai_agents/_cli/__init__.py
uipath_openai_agents/_cli/cli_new.py
uipath_openai_agents/_cli/_templates/AGENTS.md.template
uipath_openai_agents/_cli/_templates/main.py.template
uipath_openai_agents/_cli/_templates/openai_agents.json.template
uipath_openai_agents/chat/__init__.py
uipath_openai_agents/chat/openai.py
uipath_openai_agents/chat/supported_models.py
uipath_openai_agents/runtime/__init__.py
uipath_openai_agents/runtime/_serialize.py
uipath_openai_agents/runtime/agent.py
uipath_openai_agents/runtime/config.py
uipath_openai_agents/runtime/errors.py
uipath_openai_agents/runtime/factory.py
uipath_openai_agents/runtime/runtime.py
uipath_openai_agents/runtime/schema.py
uipath_openai_agents-0.0.2.dist-info/METADATA
uipath_openai_agents-0.0.2.dist-info/WHEEL
uipath_openai_agents-0.0.2.dist-info/entry_points.txt
uipath_openai_agents-0.0.2.dist-info/RECORD
