Metadata-Version: 2.4
Name: uipath-openai-agents
Version: 0.0.2
Summary: UiPath OpenAI Agents SDK
Project-URL: Homepage, https://uipath.com
Project-URL: Repository, https://github.com/UiPath/uipath-llamaindex-python
Maintainer-email: Marius Cosareanu <marius.cosareanu@uipath.com>, Cristian Pufu <cristian.pufu@uipath.com>
Classifier: Intended Audience :: Developers
Classifier: Programming Language :: Python :: 3.11
Classifier: Programming Language :: Python :: 3.12
Classifier: Programming Language :: Python :: 3.13
Classifier: Topic :: Software Development :: Build Tools
Requires-Python: >=3.11
Requires-Dist: aiosqlite>=0.20.0
Requires-Dist: openai-agents>=0.6.5
Requires-Dist: openai>=1.0.0
Requires-Dist: openinference-instrumentation-openai-agents>=1.4.0
Requires-Dist: uipath-runtime<0.6.0,>=0.5.0
Requires-Dist: uipath<2.6.0,>=2.5.0
